portalbrasil/__init__.py
portalbrasil/devsite/__init__.py
portalbrasil/devsite/_types.py
portalbrasil/devsite/configure.zcml
portalbrasil/devsite/dependencies.zcml
portalbrasil/devsite/distributions.zcml
portalbrasil/devsite/factory.py
portalbrasil/devsite/handlers.py
portalbrasil/devsite/interfaces.py
portalbrasil/devsite/permissions.zcml
portalbrasil/devsite/profiles.zcml
portalbrasil/devsite/queryparser.py
portalbrasil/devsite/content/__init__.py
portalbrasil/devsite/controlpanel/__init__.py
portalbrasil/devsite/controlpanel/configure.zcml
portalbrasil/devsite/distributions/devsite/image.png
portalbrasil/devsite/distributions/devsite/profiles.json
portalbrasil/devsite/distributions/devsite/schema.json
portalbrasil/devsite/distributions/devsite/content/.gitignore
portalbrasil/devsite/distributions/devsite/content/.gitkeep
portalbrasil/devsite/distributions/devsite/content/discussions.json
portalbrasil/devsite/distributions/devsite/content/portlets.json
portalbrasil/devsite/distributions/devsite/content/principals.json
portalbrasil/devsite/distributions/devsite/content/redirects.json
portalbrasil/devsite/distributions/devsite/content/relations.json
portalbrasil/devsite/distributions/devsite/content/translations.json
portalbrasil/devsite/distributions/devsite/content/content/__metadata__.json
portalbrasil/devsite/distributions/devsite/content/content/0a7fe46ed5e247dbb985a50990614a79/data.json
portalbrasil/devsite/distributions/devsite/content/content/21fb39c7814b40c3a25658cb0ac899bf/data.json
portalbrasil/devsite/distributions/devsite/content/content/31e9dc3c5676495d8e6d7b7f95fe930a/data.json
portalbrasil/devsite/distributions/devsite/content/content/5fe5dba47ee1495986a296cf515f0241/data.json
portalbrasil/devsite/distributions/devsite/content/content/7a05d4d192674a5b84e786b414fce0a8/data.json
portalbrasil/devsite/distributions/devsite/content/content/7a05d4d192674a5b84e786b414fce0a8/image/portalbrasil-wide-transp.png
portalbrasil_devsite-1.0.0a1.dist-info/METADATA
portalbrasil_devsite-1.0.0a1.dist-info/WHEEL
portalbrasil_devsite-1.0.0a1.dist-info/entry_points.txt
portalbrasil_devsite-1.0.0a1.dist-info/licenses/LICENSE.GPL
portalbrasil_devsite-1.0.0a1.dist-info/licenses/LICENSE.md
portalbrasil_devsite-1.0.0a1.dist-info/RECORD
